sphinx_config_options/__init__.py
sphinx_config_options/_version.py
sphinx_config_options/common.py
sphinx_config_options/directive.py
sphinx_config_options/domain.py
sphinx_config_options/_static/config-options.css
sphinx_config_options/_static/config-options.js
sphinx_config_options-0.1.0.dist-info/licenses/LICENSE
sphinx_config_options-0.1.0.dist-info/METADATA
sphinx_config_options-0.1.0.dist-info/WHEEL
sphinx_config_options-0.1.0.dist-info/top_level.txt
sphinx_config_options-0.1.0.dist-info/RECORD
